odoo_typing_classes_generator/__init__.py
odoo_typing_classes_generator/assets/template.py
odoo_typing_classes_generator/cli/__init__.py
odoo_typing_classes_generator/cli/main.py
odoo_typing_classes_generator/core/__init__.py
odoo_typing_classes_generator/core/generator.py
odoo_typing_classes_generator/core/models.py
odoo_typing_classes_generator/tests/__init__.py
odoo_typing_classes_generator/tests/test_generator.py
odoo_typing_classes_generator/tests/fake_module_1/__init__.py
odoo_typing_classes_generator/tests/fake_module_1/__manifest__.py
odoo_typing_classes_generator/tests/fake_module_1/models/__init__.py
odoo_typing_classes_generator/tests/fake_module_1/models/fake_model_1.py
odoo_typing_classes_generator/tests/fake_module_1/typing/__init__.py
odoo_typing_classes_generator-17.0.0.0.2.dist-info/licenses/LICENSE
odoo_typing_classes_generator-17.0.0.0.2.dist-info/METADATA
odoo_typing_classes_generator-17.0.0.0.2.dist-info/WHEEL
odoo_typing_classes_generator-17.0.0.0.2.dist-info/entry_points.txt
odoo_typing_classes_generator-17.0.0.0.2.dist-info/top_level.txt
odoo_typing_classes_generator-17.0.0.0.2.dist-info/RECORD
