Metadata-Version: 2.4
Name: odoo_typing_classes_generator
Version: 17.0.0.0.2
Summary: Tool to generate Odoo model type classes for better IDE support
Author-email: Alexandre Galdeano <alexandre.galdeano@gmail.com>
License:                     GNU AFFERO GENERAL PUBLIC LICENSE
Project-URL: homepage, https://github.com/alexandregaldeano/odoo-typing-classes-generator
Project-URL: documentation, https://github.com/alexandregaldeano/odoo-typing-classes-generator
Project-URL: repository, https://github.com/alexandregaldeano/odoo-typing-classes-generator
Keywords: odoo,modules,addons,typing
Classifier: License :: OSI Approved :: GNU Affero General Public License v3
Classifier: Programming Language :: Python :: 3.10
Classifier: Framework :: Odoo :: 17.0
Requires-Python: <3.11,>=3.10
License-File: LICENSE
Requires-Dist: click>=8.0
Requires-Dist: urllib3>=1.26.5
Requires-Dist: odoo
Dynamic: license-file
